kalakan/__init__.py
kalakan/api/__init__.py
kalakan/api/grpc_api.py
kalakan/api/server.py
kalakan/api/proto/tts_pb2.py
kalakan/api/proto/tts_pb2_grpc.py
kalakan/audio/__init__.py
kalakan/audio/features.py
kalakan/audio/postprocessing.py
kalakan/audio/preprocessing.py
kalakan/audio/utils.py
kalakan/cli/__init__.py
kalakan/cli/api.py
kalakan/cli/demo.py
kalakan/cli/evaluate_tts.py
kalakan/cli/gen_metadata.py
kalakan/cli/norm.py
kalakan/cli/synthesize.py
kalakan/cli/train.py
kalakan/cli/train_extended.py
kalakan/cli/train_tts.py
kalakan/data/__init__.py
kalakan/data/aligned_dataset.py
kalakan/data/augmentation.py
kalakan/data/dataset.py
kalakan/data/extended_dataset.py
kalakan/data/preprocessor.py
kalakan/models/__init__.py
kalakan/models/acoustic/__init__.py
kalakan/models/acoustic/base_acoustic.py
kalakan/models/acoustic/fastspeech2.py
kalakan/models/acoustic/tacotron2.py
kalakan/models/acoustic/transformer_tts.py
kalakan/models/components/__init__.py
kalakan/models/components/attention.py
kalakan/models/components/decoders.py
kalakan/models/components/encoders.py
kalakan/models/components/layers.py
kalakan/models/vocoders/__init__.py
kalakan/models/vocoders/base_vocoder.py
kalakan/models/vocoders/griffin_lim.py
kalakan/models/vocoders/hifigan.py
kalakan/models/vocoders/melgan.py
kalakan/models/vocoders/waveglow.py
kalakan/synthesis/__init__.py
kalakan/synthesis/synthesizer.py
kalakan/text/__init__.py
kalakan/text/cleaner.py
kalakan/text/debug_g2p.py
kalakan/text/enhanced_g2p.py
kalakan/text/enhanced_twi_g2p.py
kalakan/text/normalizer.py
kalakan/text/phonemes.py
kalakan/text/tokenizer.py
kalakan/text/twi_g2p.py
kalakan/training/__init__.py
kalakan/training/acoustic_trainer.py
kalakan/training/enhanced_acoustic_trainer.py
kalakan/training/trainer.py
kalakan/training/vocoder_trainer.py
kalakan/utils/__init__.py
kalakan/utils/audio.py
kalakan/utils/config.py
kalakan/utils/data.py
kalakan/utils/device.py
kalakan/utils/logging.py
kalakan/utils/metrics.py
kalakan_tts-1.0.1.dist-info/licenses/LICENSE
kalakan_tts-1.0.1.dist-info/METADATA
kalakan_tts-1.0.1.dist-info/WHEEL
kalakan_tts-1.0.1.dist-info/entry_points.txt
kalakan_tts-1.0.1.dist-info/top_level.txt
kalakan_tts-1.0.1.dist-info/RECORD
