Metadata-Version: 2.4
Name: kalakan-tts
Version: 1.0.1
Summary: A fully custom, offline Text-to-Speech system for the Twi language
Home-page: https://github.com/kalakan-ai/kalakan-tts
Author: Kalakan Team
Author-email: Kalakan TTS Team <calculus069@gmail.com>
License: Apache-2.0
Project-URL: Homepage, https://github.com/Odeneho-Calculus/kanakan-TTS
Project-URL: Documentation, https://github.com/Odeneho-Calculus/kanakan-TTS/tree/main/docs
Project-URL: Repository, https://github.com/Odeneho-Calculus/kanakan-TTS
Project-URL: Issues, https://github.com/Odeneho-Calculus/kanakan-TTS/issues
Project-URL: Changelog, https://github.com/Odeneho-Calculus/kanakan-TTS/releases
Keywords: tts,text-to-speech,twi,akan,pytorch,offline
Classifier: Development Status :: 4 - Beta
Classifier: Intended Audience :: Developers
Classifier: Intended Audience :: Science/Research
Classifier: License :: OSI Approved :: Apache Software License
Classifier: Operating System :: OS Independent
Classifier: Programming Language :: Python :: 3
Classifier: Programming Language :: Python :: 3.9
Classifier: Programming Language :: Python :: 3.10
Classifier: Programming Language :: Python :: 3.11
Classifier: Programming Language :: Python :: 3.12
Classifier: Topic :: Multimedia :: Sound/Audio :: Speech
Classifier: Topic :: Scientific/Engineering :: Artificial Intelligence
Classifier: Topic :: Software Development :: Libraries :: Python Modules
Requires-Python: >=3.8
License-File: LICENSE
Requires-Dist: torch>=2.0.0
Requires-Dist: torchaudio>=2.0.0
Requires-Dist: numpy>=1.21.0
Requires-Dist: librosa>=0.10.0
Requires-Dist: pydantic>=2.0.0
Requires-Dist: pyyaml>=6.0
Requires-Dist: tqdm>=4.64.0
Requires-Dist: matplotlib>=3.5.0
Requires-Dist: tensorboard>=2.10.0
Provides-Extra: dev
Requires-Dist: pytest>=7.0.0; extra == "dev"
Requires-Dist: pytest-cov>=4.0.0; extra == "dev"
Requires-Dist: black>=23.0.0; extra == "dev"
Requires-Dist: isort>=5.12.0; extra == "dev"
Requires-Dist: flake8>=6.0.0; extra == "dev"
Requires-Dist: mypy>=1.0.0; extra == "dev"
Requires-Dist: pre-commit>=3.0.0; extra == "dev"
Provides-Extra: api
Requires-Dist: fastapi>=0.100.0; extra == "api"
Requires-Dist: uvicorn>=0.23.0; extra == "api"
Requires-Dist: grpcio>=1.56.0; extra == "api"
Requires-Dist: websockets>=11.0.0; extra == "api"
Provides-Extra: training
Requires-Dist: wandb>=0.15.0; extra == "training"
Requires-Dist: mlflow>=2.5.0; extra == "training"
Requires-Dist: optuna>=3.3.0; extra == "training"
Requires-Dist: torchmetrics>=1.0.0; extra == "training"
Dynamic: author
Dynamic: home-page
Dynamic: license-file
Dynamic: requires-python
